django_fastdev/__init__.py
django_fastdev/django_app.py
django_fastdev-1.0.2.dist-info/LICENSE
django_fastdev-1.0.2.dist-info/METADATA
django_fastdev-1.0.2.dist-info/WHEEL
django_fastdev-1.0.2.dist-info/top_level.txt
django_fastdev-1.0.2.dist-info/RECORD
