Metadata-Version: 2.1
Name: django-fastdev
Version: 1.0.2
Summary: Django-fastdev is an app that makes it faster and more fun to develop Django apps
Home-page: https://github.com/boxed/django-fastdev
Author: Anders Hovmöller
Author-email: boxed@killingar.net
License: BSD
Keywords: django
Platform: UNKNOWN
Classifier: Development Status :: 5 - Production/Stable
Classifier: Intended Audience :: Developers
Classifier: License :: OSI Approved :: BSD License
Classifier: Natural Language :: English
Classifier: Programming Language :: Python :: 3
Classifier: Programming Language :: Python :: 3.7
Requires-Dist: Django (>=3.0)
